{"@context":"https://iiif.io/api/presentation/3/context.json","id":"https://tonothan.github.io/sangaku-archive/api/facet/year/71810.json","type":"Collection","label":{"none":["文化7年・1810"]},"items":[{"id":"https://sangaku-archive.org/app/api/sangaku_manifests/3/1810_Toyama_Asahiyama_493.json","type":"Manifest","label":{"none":["富山県朝日山観音堂の算額 (算額題)・Sangaku of Asahiyama Kannon Hall, Toyama (Sangaku problem)"]},"thumbnail":[{"id":"https://sangaku-archive.org/iiif/3/RB00028475_00118_0.ptiff/full/!200,200/0/default.jpg","type":"Image","format":"image/jpeg","width":200,"height":150,"viewingDirection":"right-to-left","behavior":["individuals"],"service":[{"id":"https://sangaku-archive.org/iiif/3/RB00028475_00118_0.ptiff","type":"ImageService3","profile":"level1"}]}],"homepage":[{"id":"https://tonothan.github.io/sangaku-archive/works/1810_Toyama_Asahiyama_493","type":"Text","label":{"none":["富山県朝日山観音堂の算額 (算額題)・Sangaku of Asahiyama Kannon Hall, Toyama (Sangaku problem)"]}}]},{"id":"https://sangaku-archive.org/app/api/sangaku_manifests/3/1810_Ishikawa_Isurugihiko_494.json","type":"Manifest","label":{"none":["石川県伊須流岐比古神社の算額 (算額題)・Sangaku of Isurugihiko Shrine, Ishikawa (Sangaku problem)"]},"thumbnail":[{"id":"https://sangaku-archive.org/iiif/3/RB00028475_00119_0.ptiff/full/!200,200/0/default.jpg","type":"Image","format":"image/jpeg","width":200,"height":150,"viewingDirection":"right-to-left","behavior":["individuals"],"service":[{"id":"https://sangaku-archive.org/iiif/3/RB00028475_00119_0.ptiff","type":"ImageService3","profile":"level1"}]}],"homepage":[{"id":"https://tonothan.github.io/sangaku-archive/works/1810_Ishikawa_Isurugihiko_494","type":"Text","label":{"none":["石川県伊須流岐比古神社の算額 (算額題)・Sangaku of Isurugihiko Shrine, Ishikawa (Sangaku problem)"]}}]}],"partOf":[{"id":"https://tonothan.github.io/sangaku-archive/api/facet/year.json","type":"Collection"}],"summary":{"none":["年・ Year"]},"homepage":[{"id":"https://tonothan.github.io/sangaku-archive/search?year=71810","type":"Text","label":{"none":["文化7年・1810"]}}]}