{"@context":"https://iiif.io/api/presentation/3/context.json","id":"https://tonothan.github.io/sangaku-archive/api/facet/author/matsushita-yoshimasa.json","type":"Collection","label":{"none":["丸山良玄門人松下与昌・ Matsushita Yoshimasa"]},"items":[{"id":"https://tonothan.github.io/1800_Niigata_Sanjubanshin.json","type":"Manifest","label":{"none":["新潟県三十番神の算額 (続神壁算法)・Sangaku of Sanjubanshin Hall, Niigata (Zoku Shinpeki Sanpou)"]},"thumbnail":[{"id":"https://sangaku-archive.org/iiif/3//full/!200,200/0/default.jpg","type":"Image","format":"image/jpeg","width":200,"height":150,"viewingDirection":"right-to-left","behavior":["individuals"],"service":[{"id":"https://sangaku-archive.org/iiif/3/","type":"ImageService3","profile":"level1"}]}],"homepage":[{"id":"https://tonothan.github.io/sangaku-archive/works/sangaku-of-sanjubanshin-hall-niigata-zoku-shinpeki-sanpou","type":"Text","label":{"none":["新潟県三十番神の算額 (続神壁算法)・Sangaku of Sanjubanshin Hall, Niigata (Zoku Shinpeki Sanpou)"]}}]}],"partOf":[{"id":"https://tonothan.github.io/sangaku-archive/api/facet/author.json","type":"Collection"}],"summary":{"none":["奉納者・ Author"]},"homepage":[{"id":"https://tonothan.github.io/sangaku-archive/search?author=matsushita-yoshimasa","type":"Text","label":{"none":["丸山良玄門人松下与昌・ Matsushita Yoshimasa"]}}]}