{"@context":"https://iiif.io/api/presentation/3/context.json","id":"https://sangaku-archive.org/api/facet/dedicator/kikuchi-joko.json","type":"Collection","label":{"none":["菊池如好・Kikuchi Joko"]},"items":[{"id":"https://sangaku-archive.com/app/api/sangaku_manifests/3/1808_Iwate_Komagata_1639.json","type":"Manifest","label":{"en":["Komagata Shrine, Iwate, 1808 (Original)."],"ja":["岩手県, 駒形神社, 文化5年4月 (現物)."],"none":["岩手県, 駒形神社, 文化5年4月 (現物). / Komagata Shrine, Iwate, 1808 (Original)."]},"thumbnail":[{"id":"https://sangaku-archive.com/iiif/3/1808_Iwate_Komagata_1639.ptiff/full/!200,200/0/default.jpg","type":"Image","format":"image/jpeg","width":200,"height":150,"service":[{"id":"https://sangaku-archive.com/iiif/3/1808_Iwate_Komagata_1639.ptiff","type":"ImageService3","profile":"level2"}]}],"homepage":[{"id":"https://sangaku-archive.org/works/1808_Iwate_Komagata_1639","type":"Text","label":{"en":["Komagata Shrine, Iwate, 1808 (Original)."],"ja":["岩手県, 駒形神社, 文化5年4月 (現物)."],"none":["岩手県, 駒形神社, 文化5年4月 (現物). / Komagata Shrine, Iwate, 1808 (Original)."]}}]},{"id":"https://sangaku-archive.com/app/api/sangaku_manifests/3/1808_Iwate_Komagata_1806.json","type":"Manifest","label":{"en":["Komagata Shrine, Iwate, 1808 (Replica)."],"ja":["岩手県, 駒形神社, 文化54月 (復元)."],"none":["岩手県, 駒形神社, 文化54月 (復元). / Komagata Shrine, Iwate, 1808 (Replica)."]},"thumbnail":[{"id":"https://sangaku-archive.com/iiif/3/1808_Iwate_Komagata_1806.ptiff/full/!200,200/0/default.jpg","type":"Image","format":"image/jpeg","width":200,"height":150,"service":[{"id":"https://sangaku-archive.com/iiif/3/1808_Iwate_Komagata_1806.ptiff","type":"ImageService3","profile":"level2"}]}],"homepage":[{"id":"https://sangaku-archive.org/works/1808_Iwate_Komagata_1806","type":"Text","label":{"en":["Komagata Shrine, Iwate, 1808 (Replica)."],"ja":["岩手県, 駒形神社, 文化54月 (復元)."],"none":["岩手県, 駒形神社, 文化54月 (復元). / Komagata Shrine, Iwate, 1808 (Replica)."]}}]}],"partOf":[{"id":"https://sangaku-archive.org/api/facet/dedicator.json","type":"Collection"}],"summary":{"none":["奉納者・ Dedicator"]},"homepage":[{"id":"https://sangaku-archive.org/search?dedicator=kikuchi-joko","type":"Text","label":{"none":["菊池如好・Kikuchi Joko"]}}]}