{"@context":"https://iiif.io/api/presentation/3/context.json","id":"https://tonothan.github.io/sangaku-archive/api/facet/dedicator/nobufusa-enomoto.json","type":"Collection","label":{"none":["丸田政道門人榎本信房・Nobufusa Enomoto"]},"items":[{"id":"https://sangaku-archive.org/app/api/sangaku_manifests/3/1807_Niigata_Otohoji_1355.json","type":"Manifest","label":{"none":["新潟県乙宝寺大日堂の算額 (賽祠神筭)・Sangaku of Otohoji Temple Dainichi Hall, Niigata  (Saishi Shinsan)"]},"thumbnail":[{"id":"https://sangaku-archive.org/iiif/3/saishishinsan-4_R0000025.jpg/full/!200,200/0/default.jpg","type":"Image","format":"image/jpeg","width":200,"height":150,"viewingDirection":"right-to-left","behavior":["individuals"],"service":[{"id":"https://sangaku-archive.org/iiif/3/saishishinsan-4_R0000025.jpg","type":"ImageService3","profile":"level1"}]}],"homepage":[{"id":"https://tonothan.github.io/sangaku-archive/works/1807_Niigata_Otohoji_1355","type":"Text","label":{"none":["新潟県乙宝寺大日堂の算額 (賽祠神筭)・Sangaku of Otohoji Temple Dainichi Hall, Niigata  (Saishi Shinsan)"]}}]}],"partOf":[{"id":"https://tonothan.github.io/sangaku-archive/api/facet/dedicator.json","type":"Collection"}],"summary":{"none":["奉納者・ Dedicator"]},"homepage":[{"id":"https://tonothan.github.io/sangaku-archive/search?dedicator=nobufusa-enomoto","type":"Text","label":{"none":["丸田政道門人榎本信房・Nobufusa Enomoto"]}}]}