{"@context":"https://iiif.io/api/presentation/3/context.json","id":"https://tonothan.github.io/sangaku-archive/api/facet/dedicator/norisada-miyai-disciple-of-yasushi-uchida.json","type":"Collection","label":{"none":["内田恭門人宮井則定・Norisada Miyai, disciple of Yasushi Uchida"]},"items":[{"id":"https://sangaku-archive.org/app/api/sangaku_manifests/3/1826_Kanagawa_Tsurugaoka_1849.json","type":"Manifest","label":{"en":["Tsurugaoka Hachimangu Shrine, Kanagawa, 1826 (Sangaku problem)."],"ja":["神奈川県, 鶴岡八幡宮, 文政9年 (算額題)."],"none":["神奈川県, 鶴岡八幡宮, 文政9年 (算額題). / Tsurugaoka Hachimangu Shrine, Kanagawa, 1826 (Sangaku problem)."]},"thumbnail":[{"id":"https://sangaku-archive.org/iiif/3/1826_Kanagawa_Tsurugaoka_1849.ptiff/full/!200,200/0/default.jpg","type":"Image","format":"image/jpeg","width":200,"height":150,"service":[{"id":"https://sangaku-archive.org/iiif/3/1826_Kanagawa_Tsurugaoka_1849.ptiff","type":"ImageService3","profile":"level2"}]}],"homepage":[{"id":"https://tonothan.github.io/sangaku-archive/works/1826_Kanagawa_Tsurugaoka_1849","type":"Text","label":{"en":["Tsurugaoka Hachimangu Shrine, Kanagawa, 1826 (Sangaku problem)."],"ja":["神奈川県, 鶴岡八幡宮, 文政9年 (算額題)."],"none":["神奈川県, 鶴岡八幡宮, 文政9年 (算額題). / Tsurugaoka Hachimangu Shrine, Kanagawa, 1826 (Sangaku problem)."]}}]}],"partOf":[{"id":"https://tonothan.github.io/sangaku-archive/api/facet/dedicator.json","type":"Collection"}],"summary":{"none":["奉納者・ Dedicator"]},"homepage":[{"id":"https://tonothan.github.io/sangaku-archive/search?dedicator=norisada-miyai-disciple-of-yasushi-uchida","type":"Text","label":{"none":["内田恭門人宮井則定・Norisada Miyai, disciple of Yasushi Uchida"]}}]}