{"@context":"https://iiif.io/api/presentation/3/context.json","id":"https://tonothan.github.io/sangaku-archive/api/facet/dedicator/rokuro-chiba-tanenoris-disciple-kohei-ishikawa.json","type":"Collection","label":{"none":["千葉六郎胤規門人石川幸平・Rokuro Chiba Tanenori's disciple, Kohei Ishikawa"]},"items":[{"id":"https://sangaku-archive.org/app/api/sangaku_manifests/3/1912_Miyagi_Shiogama_1095.json","type":"Manifest","label":{"none":["宮城県鹽竈神社の算額 (現物)・Sangaku of Shiogama Shrine, Miyagi (Original)"]},"thumbnail":[{"id":"https://sangaku-archive.org/iiif/3/1912_Miyagi_Shiogama_1095.ptiff/full/!200,200/0/default.jpg","type":"Image","format":"image/jpeg","width":200,"height":150,"viewingDirection":"right-to-left","behavior":["individuals"],"service":[{"id":"https://sangaku-archive.org/iiif/3/1912_Miyagi_Shiogama_1095.ptiff","type":"ImageService3","profile":"level1"}]}],"homepage":[{"id":"https://tonothan.github.io/sangaku-archive/works/1912_Miyagi_Shiogama_1095","type":"Text","label":{"none":["宮城県鹽竈神社の算額 (現物)・Sangaku of Shiogama Shrine, Miyagi (Original)"]}}]}],"partOf":[{"id":"https://tonothan.github.io/sangaku-archive/api/facet/dedicator.json","type":"Collection"}],"summary":{"none":["奉納者・ Dedicator"]},"homepage":[{"id":"https://tonothan.github.io/sangaku-archive/search?dedicator=rokuro-chiba-tanenoris-disciple-kohei-ishikawa","type":"Text","label":{"none":["千葉六郎胤規門人石川幸平・Rokuro Chiba Tanenori's disciple, Kohei Ishikawa"]}}]}