{"@context":"https://iiif.io/api/presentation/3/context.json","id":"https://tonothan.github.io/sangaku-archive/api/facet/dedication-site/aoshiba-shrine.json","type":"Collection","label":{"none":["蒼柴明神社・Aoshiba Shrine"]},"items":[{"id":"https://sangaku-archive.org/app/api/sangaku_manifests/3/1801_Niigata_Aoshiba_1308.json","type":"Manifest","label":{"none":["新潟県蒼柴明神社の算額 (賽祠神筭)・Sangaku of Aoshiba Shrine, Niigata  (Saishi Shinsan)"]},"thumbnail":[{"id":"https://sangaku-archive.org/iiif/3/saishishinsan-3_R0000003.ptiff/full/!200,200/0/default.jpg","type":"Image","format":"image/jpeg","width":200,"height":150,"viewingDirection":"right-to-left","behavior":["individuals"],"service":[{"id":"https://sangaku-archive.org/iiif/3/saishishinsan-3_R0000003.ptiff","type":"ImageService3","profile":"level1"}]}],"homepage":[{"id":"https://tonothan.github.io/sangaku-archive/works/1801_Niigata_Aoshiba_1308","type":"Text","label":{"none":["新潟県蒼柴明神社の算額 (賽祠神筭)・Sangaku of Aoshiba Shrine, Niigata  (Saishi Shinsan)"]}}]},{"id":"https://sangaku-archive.org/app/api/sangaku_manifests/3/1798_Niigata_Aoshiba_1297.json","type":"Manifest","label":{"none":["新潟県蒼柴明神社の算額 (賽祠神筭)・Sangaku of Aoshiba Shrine, Niigata  (Saishi Shinsan)"]},"thumbnail":[{"id":"https://sangaku-archive.org/iiif/3/saishishinsan-2_R0000031.ptiff/full/!200,200/0/default.jpg","type":"Image","format":"image/jpeg","width":200,"height":150,"viewingDirection":"right-to-left","behavior":["individuals"],"service":[{"id":"https://sangaku-archive.org/iiif/3/saishishinsan-2_R0000031.ptiff","type":"ImageService3","profile":"level1"}]}],"homepage":[{"id":"https://tonothan.github.io/sangaku-archive/works/1798_Niigata_Aoshiba_1297","type":"Text","label":{"none":["新潟県蒼柴明神社の算額 (賽祠神筭)・Sangaku of Aoshiba Shrine, Niigata  (Saishi Shinsan)"]}}]}],"partOf":[{"id":"https://tonothan.github.io/sangaku-archive/api/facet/dedication-site.json","type":"Collection"}],"summary":{"none":["奉納所・ Dedication site"]},"homepage":[{"id":"https://tonothan.github.io/sangaku-archive/search?dedication-site=aoshiba-shrine","type":"Text","label":{"none":["蒼柴明神社・Aoshiba Shrine"]}}]}