{"@context":"https://iiif.io/api/presentation/3/context.json","id":"https://tonothan.github.io/sangaku-archive/api/facet/dedication-site/hakun-mountain.json","type":"Collection","label":{"none":["白雲山 ・ Hakun Mountain"]},"items":[],"partOf":[{"id":"https://tonothan.github.io/sangaku-archive/api/facet/dedication-site.json","type":"Collection"}],"summary":{"none":["奉納所・ Dedication site"]},"homepage":[{"id":"https://tonothan.github.io/sangaku-archive/search?dedication-site=hakun-mountain","type":"Text","label":{"none":["白雲山 ・ Hakun Mountain"]}}]}