{"@context":"https://iiif.io/api/presentation/3/context.json","id":"https://tonothan.github.io/sangaku-archive/api/facet/dedication-site/hojozu-hachiman-shrine.json","type":"Collection","label":{"none":["放生津八幡宮・Hojozu Hachiman Shrine"]},"items":[{"id":"https://sangaku-archive.org/app/api/sangaku_manifests/3/1783_Toyama_Hojozu_902.json","type":"Manifest","label":{"none":["富山県放生津八幡宮の算額 (復元)・Sangaku of Hojozu Hachiman Shrine, Toyama (Replica)"]},"thumbnail":[{"id":"https://sangaku-archive.org/iiif/3/1783_Toyama_Hojozu_902.ptiff/full/!200,200/0/default.jpg","type":"Image","format":"image/jpeg","width":200,"height":150,"viewingDirection":"right-to-left","behavior":["individuals"],"service":[{"id":"https://sangaku-archive.org/iiif/3/1783_Toyama_Hojozu_902.ptiff","type":"ImageService3","profile":"level1"}]}],"homepage":[{"id":"https://tonothan.github.io/sangaku-archive/works/1783_Toyama_Hojozu_902","type":"Text","label":{"none":["富山県放生津八幡宮の算額 (復元)・Sangaku of Hojozu Hachiman Shrine, Toyama (Replica)"]}}]},{"id":"https://sangaku-archive.org/app/api/sangaku_manifests/3/2022_Toyama_Hojozu_922.json","type":"Manifest","label":{"none":["富山県放生津八幡宮の算額 (現物)・Sangaku of Hojozu Hachiman Shrine, Toyama (Original)"]},"thumbnail":[{"id":"https://sangaku-archive.org/iiif/3/2022_Toyama_Hojozu_922.ptiff/full/!200,200/0/default.jpg","type":"Image","format":"image/jpeg","width":200,"height":150,"viewingDirection":"right-to-left","behavior":["individuals"],"service":[{"id":"https://sangaku-archive.org/iiif/3/2022_Toyama_Hojozu_922.ptiff","type":"ImageService3","profile":"level1"}]}],"homepage":[{"id":"https://tonothan.github.io/sangaku-archive/works/2022_Toyama_Hojozu_922","type":"Text","label":{"none":["富山県放生津八幡宮の算額 (現物)・Sangaku of Hojozu Hachiman Shrine, Toyama (Original)"]}}]},{"id":"https://sangaku-archive.org/app/api/sangaku_manifests/3/1783_Toyama_Hojozu_482.json","type":"Manifest","label":{"none":["富山県放生津八幡宮の算額 (算額題)・Sangaku of Hojozu Hachiman Shrine, Toyama (Sangaku problem)"]},"thumbnail":[{"id":"https://sangaku-archive.org/iiif/3/RB00028475_00103_0.ptiff/full/!200,200/0/default.jpg","type":"Image","format":"image/jpeg","width":200,"height":150,"viewingDirection":"right-to-left","behavior":["individuals"],"service":[{"id":"https://sangaku-archive.org/iiif/3/RB00028475_00103_0.ptiff","type":"ImageService3","profile":"level1"}]}],"homepage":[{"id":"https://tonothan.github.io/sangaku-archive/works/1783_Toyama_Hojozu_482","type":"Text","label":{"none":["富山県放生津八幡宮の算額 (算額題)・Sangaku of Hojozu Hachiman Shrine, Toyama (Sangaku problem)"]}}]},{"id":"https://sangaku-archive.org/app/api/sangaku_manifests/3/1805_Toyama_Hojozu_489.json","type":"Manifest","label":{"none":["富山県放生津八幡宮の算額 (算額題)・Sangaku of Hojozu Hachiman Shrine, Toyama (Sangaku problem)"]},"thumbnail":[{"id":"https://sangaku-archive.org/iiif/3/RB00028475_00112_0.ptiff/full/!200,200/0/default.jpg","type":"Image","format":"image/jpeg","width":200,"height":150,"viewingDirection":"right-to-left","behavior":["individuals"],"service":[{"id":"https://sangaku-archive.org/iiif/3/RB00028475_00112_0.ptiff","type":"ImageService3","profile":"level1"}]}],"homepage":[{"id":"https://tonothan.github.io/sangaku-archive/works/1805_Toyama_Hojozu_489","type":"Text","label":{"none":["富山県放生津八幡宮の算額 (算額題)・Sangaku of Hojozu Hachiman Shrine, Toyama (Sangaku problem)"]}}]},{"id":"https://sangaku-archive.org/app/api/sangaku_manifests/3/1807_Toyama_Hojozu_490.json","type":"Manifest","label":{"none":["富山県放生津八幡宮の算額 (算額題)・Sangaku of Hojozu Hachiman Shrine, Toyama (Sangaku problem)"]},"thumbnail":[{"id":"https://sangaku-archive.org/iiif/3/RB00028475_00114_0.ptiff/full/!200,200/0/default.jpg","type":"Image","format":"image/jpeg","width":200,"height":150,"viewingDirection":"right-to-left","behavior":["individuals"],"service":[{"id":"https://sangaku-archive.org/iiif/3/RB00028475_00114_0.ptiff","type":"ImageService3","profile":"level1"}]}],"homepage":[{"id":"https://tonothan.github.io/sangaku-archive/works/1807_Toyama_Hojozu_490","type":"Text","label":{"none":["富山県放生津八幡宮の算額 (算額題)・Sangaku of Hojozu Hachiman Shrine, Toyama (Sangaku problem)"]}}]}],"partOf":[{"id":"https://tonothan.github.io/sangaku-archive/api/facet/dedication-site.json","type":"Collection"}],"summary":{"none":["奉納所・ Dedication site"]},"homepage":[{"id":"https://tonothan.github.io/sangaku-archive/search?dedication-site=hojozu-hachiman-shrine","type":"Text","label":{"none":["放生津八幡宮・Hojozu Hachiman Shrine"]}}]}