{"@context":"https://iiif.io/api/presentation/3/context.json","id":"https://sangaku-archive.org/api/facet/dedication-site/jinguji.json","type":"Collection","label":{"none":["神宮寺・Jinguji"]},"items":[{"id":"https://sangaku-archive.com/app/api/sangaku_manifests/3/1899_Shizuoka_Jinguji_1462.json","type":"Manifest","label":{"en":["Jinguji, Shizuoka, 1899 (Replica)."],"ja":["静岡県, 神宮寺, 明治32年3月 (復元)."],"none":["静岡県, 神宮寺, 明治32年3月 (復元). / Jinguji, Shizuoka, 1899 (Replica)."]},"thumbnail":[{"id":"https://sangaku-archive.com/iiif/3/1899_Shizuoka_Jinguji_1462.ptiff/full/!200,200/0/default.jpg","type":"Image","format":"image/jpeg","width":200,"height":150,"service":[{"id":"https://sangaku-archive.com/iiif/3/1899_Shizuoka_Jinguji_1462.ptiff","type":"ImageService3","profile":"level2"}]}],"homepage":[{"id":"https://sangaku-archive.org/works/1899_Shizuoka_Jinguji_1462","type":"Text","label":{"en":["Jinguji, Shizuoka, 1899 (Replica)."],"ja":["静岡県, 神宮寺, 明治32年3月 (復元)."],"none":["静岡県, 神宮寺, 明治32年3月 (復元). / Jinguji, Shizuoka, 1899 (Replica)."]}}]}],"partOf":[{"id":"https://sangaku-archive.org/api/facet/dedication-site.json","type":"Collection"}],"summary":{"none":["奉納所・ Dedication site"]},"homepage":[{"id":"https://sangaku-archive.org/search?dedication-site=jinguji","type":"Text","label":{"none":["神宮寺・Jinguji"]}}]}