{"@context":"https://iiif.io/api/presentation/3/context.json","id":"https://sangaku-archive.org/api/facet/dedication-site/matsuzaka-tenjin-shrine.json","type":"Collection","label":{"none":["松阪天神・Matsuzaka Tenjin Shrine"]},"items":[{"id":"https://sangaku-archive.com/app/api/sangaku_manifests/3/1804_Mie_Matsuzaka_2193.json","type":"Manifest","label":{"en":["Matsuzaka Tenjin Shrine, Mie, 1804 (null)."],"ja":["三重県, 松阪天神, 文化元年 (書面記録)."],"none":["三重県, 松阪天神, 文化元年 (書面記録). / Matsuzaka Tenjin Shrine, Mie, 1804 (null)."]},"thumbnail":[{"id":"https://sangaku-archive.com/iiif/3/1751592169073-ed87d8f9-ba86-4f8b-8a12-c7b533c4fd1a_43L.ptiff/full/!200,200/0/default.jpg","type":"Image","format":"image/jpeg","width":200,"height":150,"service":[{"id":"https://sangaku-archive.com/iiif/3/1751592169073-ed87d8f9-ba86-4f8b-8a12-c7b533c4fd1a_43L.ptiff","type":"ImageService3","profile":"level2"}]}],"homepage":[{"id":"https://sangaku-archive.org/works/1804_Mie_Matsuzaka_2193","type":"Text","label":{"en":["Matsuzaka Tenjin Shrine, Mie, 1804 (null)."],"ja":["三重県, 松阪天神, 文化元年 (書面記録)."],"none":["三重県, 松阪天神, 文化元年 (書面記録). / Matsuzaka Tenjin Shrine, Mie, 1804 (null)."]}}]}],"partOf":[{"id":"https://sangaku-archive.org/api/facet/dedication-site.json","type":"Collection"}],"summary":{"none":["奉納所・ Dedication site"]},"homepage":[{"id":"https://sangaku-archive.org/search?dedication-site=matsuzaka-tenjin-shrine","type":"Text","label":{"none":["松阪天神・Matsuzaka Tenjin Shrine"]}}]}