{"@context":"https://iiif.io/api/presentation/3/context.json","id":"https://tonothan.github.io/sangaku-archive/api/facet/dedication-site/nawa-shimmei-shrine.json","type":"Collection","label":{"none":["那波神明宮 ・ Nawa Shimmei Shrine"]},"items":[{"id":"https://tonothan.github.io/1806_Gumma_Nawa.json","type":"Manifest","label":{"none":["群馬県那波神明宮の算額 (続神壁算法)・Sangaku of Nawa Shimmei Shrine, Gumma (Zoku Shinpeki Sanpou)"]},"thumbnail":[{"id":"https://sangaku-archive.org/iiif/3//full/!200,200/0/default.jpg","type":"Image","format":"image/jpeg","width":200,"height":150,"viewingDirection":"right-to-left","behavior":["individuals"],"service":[{"id":"https://sangaku-archive.org/iiif/3/","type":"ImageService3","profile":"level1"}]}],"homepage":[{"id":"https://tonothan.github.io/sangaku-archive/works/sangaku-of-nawa-shimmei-shrine-gumma-zoku-shinpeki-sanpou","type":"Text","label":{"none":["群馬県那波神明宮の算額 (続神壁算法)・Sangaku of Nawa Shimmei Shrine, Gumma (Zoku Shinpeki Sanpou)"]}}]}],"partOf":[{"id":"https://tonothan.github.io/sangaku-archive/api/facet/dedication-site.json","type":"Collection"}],"summary":{"none":["奉納所・ Dedication site"]},"homepage":[{"id":"https://tonothan.github.io/sangaku-archive/search?dedication-site=nawa-shimmei-shrine","type":"Text","label":{"none":["那波神明宮 ・ Nawa Shimmei Shrine"]}}]}